keton/__init__.py
keton/ai/__init__.py
keton/ai/torch/__init__.py
keton/ai/torch/callbacks/__init__.py
keton/ai/torch/callbacks/common.py
keton/ai/torch/callbacks/logger.py
keton/ai/torch/callbacks/model.py
keton/ai/torch/callbacks/scheduler.py
keton/ai/torch/losses/__init__.py
keton/ai/torch/losses/classification.py
keton/ai/torch/metrics.py
keton/ai/torch/models/__init__.py
keton/ai/torch/models/alexnet.py
keton/ai/torch/models/common.py
keton/ai/torch/models/efficientnet.py
keton/ai/torch/models/regnet.py
keton/ai/torch/models/resnet.py
keton/ai/torch/models/vit.py
keton/ai/torch/trainer.py
keton/ai/torch/utils/__init__.py
keton/ai/torch/utils/functions.py
keton/ai/torch/utils/modules.py
keton/common/__init__.py
keton/common/dcm/README.md
keton/common/dcm/__init__.py
keton/common/dcm/configs.py
keton-0.1.5.dist-info/WHEEL
keton-0.1.5.dist-info/METADATA
keton-0.1.5.dist-info/RECORD
